{"type":"Feature","properties":{"name":"Addis Ababa","founded":"","abandoned":"","source":"https://en.wikipedia.org/wiki/Addis Ababa","note":""},"geometry":{"coordinates":[8.9806034,38.7577605],"type":"Point"}}