{"type":"Feature","properties":{"name":"Almaty","founded":"","abandoned":"","source":"https://en.wikipedia.org/wiki/Almaty","note":""},"geometry":{"coordinates":[43.2220146,76.8512485],"type":"Point"}}