{"type":"Feature","properties":{"name":"Baltimore","founded":"","abandoned":"","source":"https://en.wikipedia.org/wiki/Baltimore","note":""},"geometry":{"coordinates":[39.2903848,-76.6121893],"type":"Point"}}