{"type":"Feature","properties":{"name":"Bamako","founded":"","abandoned":"","source":"https://en.wikipedia.org/wiki/Bamako","note":""},"geometry":{"coordinates":[12.6392316,-8.0028892],"type":"Point"}}