{"type":"Feature","properties":{"name":"Bangalore","founded":"","abandoned":"","source":"https://en.wikipedia.org/wiki/Bangalore","note":""},"geometry":{"coordinates":[12.9715987,77.5945627],"type":"Point"}}