{"type":"Feature","properties":{"name":"Birkirkara","founded":"","abandoned":"","source":"https://en.wikipedia.org/wiki/Birkirkara","note":""},"geometry":{"coordinates":[35.8954706,14.4665072],"type":"Point"}}