{"type":"Feature","properties":{"name":"Birmingham","founded":"","abandoned":"","source":"https://en.wikipedia.org/wiki/Birmingham","note":""},"geometry":{"coordinates":[52.48624299999999,-1.890401],"type":"Point"}}