{"type":"Feature","properties":{"name":"Bridgetown","founded":"","abandoned":"","source":"https://en.wikipedia.org/wiki/Bridgetown","note":""},"geometry":{"coordinates":[13.0968511,-59.61448189999999],"type":"Point"}}