{"type":"Feature","properties":{"name":"Budapest","founded":"","abandoned":"","source":"https://en.wikipedia.org/wiki/Budapest","note":""},"geometry":{"coordinates":[47.497912,19.040235],"type":"Point"}}