{"type":"Feature","properties":{"name":"Cambridge","founded":"","abandoned":"","source":"https://en.wikipedia.org/wiki/Cambridge","note":""},"geometry":{"coordinates":[52.205337,0.121817],"type":"Point"}}