{"type":"Feature","properties":{"name":"Cape Town","founded":"","abandoned":"","source":"https://en.wikipedia.org/wiki/Cape Town","note":""},"geometry":{"coordinates":[-33.9248685,18.4240553],"type":"Point"}}