{"type":"Feature","properties":{"name":"Casablanca","founded":"","abandoned":"","source":"https://en.wikipedia.org/wiki/Casablanca","note":""},"geometry":{"coordinates":[33.5731104,-7.589843399999999],"type":"Point"}}