{"type":"Feature","properties":{"name":"Charlotte","founded":"","abandoned":"","source":"https://en.wikipedia.org/wiki/Charlotte","note":""},"geometry":{"coordinates":[35.2270869,-80.8431267],"type":"Point"}}