{"type":"Feature","properties":{"name":"Charlotte Amalie","founded":"","abandoned":"","source":"https://en.wikipedia.org/wiki/Charlotte Amalie","note":""},"geometry":{"coordinates":[18.3419004,-64.9307007],"type":"Point"}}