{"type":"Feature","properties":{"name":"Chelyabinsk","founded":"","abandoned":"","source":"https://en.wikipedia.org/wiki/Chelyabinsk","note":""},"geometry":{"coordinates":[55.1644419,61.4368432],"type":"Point"}}