{"type":"Feature","properties":{"name":"Chittagong","founded":"","abandoned":"","source":"https://en.wikipedia.org/wiki/Chittagong","note":""},"geometry":{"coordinates":[22.356851,91.7831819],"type":"Point"}}