{"type":"Feature","properties":{"name":"Ciudad Bolívar","founded":"","abandoned":"","source":"https://en.wikipedia.org/wiki/Ciudad Bolívar","note":""},"geometry":{"coordinates":[8.088279100000001,-63.5535552],"type":"Point"}}