{"type":"Feature","properties":{"name":"Concepción","founded":"","abandoned":"","source":"https://en.wikipedia.org/wiki/Concepción","note":""},"geometry":{"coordinates":[-36.8201352,-73.0443904],"type":"Point"}}