{"type":"Feature","properties":{"name":"Craiova","founded":"","abandoned":"","source":"https://en.wikipedia.org/wiki/Craiova","note":""},"geometry":{"coordinates":[44.3301785,23.7948807],"type":"Point"}}