{"type":"Feature","properties":{"name":"Cúcuta","founded":"","abandoned":"","source":"https://en.wikipedia.org/wiki/Cúcuta","note":""},"geometry":{"coordinates":[7.8890971,-72.4966896],"type":"Point"}}