{"type":"Feature","properties":{"name":"Dar es Salaam","founded":"","abandoned":"","source":"https://en.wikipedia.org/wiki/Dar es Salaam","note":""},"geometry":{"coordinates":[-6.792354,39.2083284],"type":"Point"}}