{"type":"Feature","properties":{"name":"Flores Island","founded":"","abandoned":"","source":"https://en.wikipedia.org/wiki/Flores Island","note":""},"geometry":{"coordinates":[39.4474713,-31.193945],"type":"Point"}}