{"type":"Feature","properties":{"name":"Fortaleza","founded":"","abandoned":"","source":"https://en.wikipedia.org/wiki/Fortaleza","note":""},"geometry":{"coordinates":[-3.7319029,-38.5267393],"type":"Point"}}