{"type":"Feature","properties":{"name":"Fort-de-France","founded":"","abandoned":"","source":"https://en.wikipedia.org/wiki/Fort-de-France","note":""},"geometry":{"coordinates":[14.6160647,-61.0587804],"type":"Point"}}