{"type":"Feature","properties":{"name":"Freetown","founded":"","abandoned":"","source":"https://en.wikipedia.org/wiki/Freetown","note":""},"geometry":{"coordinates":[8.4656765,-13.2317225],"type":"Point"}}