{"type":"Feature","properties":{"name":"Guatemala City","founded":"","abandoned":"","source":"https://en.wikipedia.org/wiki/Guatemala City","note":""},"geometry":{"coordinates":[14.6349149,-90.5068824],"type":"Point"}}