{"type":"Feature","properties":{"name":"Haarlem","founded":"","abandoned":"","source":"https://en.wikipedia.org/wiki/Haarlem","note":""},"geometry":{"coordinates":[52.3873878,4.6462194],"type":"Point"}}