{"type":"Feature","properties":{"name":"Iquique","founded":"","abandoned":"","source":"https://en.wikipedia.org/wiki/Iquique","note":""},"geometry":{"coordinates":[-20.2307033,-70.1356692],"type":"Point"}}