{"type":"Feature","properties":{"name":"Jersey City","founded":"","abandoned":"","source":"https://en.wikipedia.org/wiki/Jersey City","note":""},"geometry":{"coordinates":[40.72815749999999,-74.0776417],"type":"Point"}}