{"type":"Feature","properties":{"name":"João Pessoa","founded":"","abandoned":"","source":"https://en.wikipedia.org/wiki/João Pessoa","note":""},"geometry":{"coordinates":[-7.119495799999999,-34.8450118],"type":"Point"}}