{"type":"Feature","properties":{"name":"Juiz de Fora","founded":"","abandoned":"","source":"https://en.wikipedia.org/wiki/Juiz de Fora","note":""},"geometry":{"coordinates":[-21.7624237,-43.3433999],"type":"Point"}}