{"type":"Feature","properties":{"name":"Kanpur","founded":"","abandoned":"","source":"https://en.wikipedia.org/wiki/Kanpur","note":""},"geometry":{"coordinates":[26.449923,80.3318736],"type":"Point"}}