{"type":"Feature","properties":{"name":"Kansas City","founded":"","abandoned":"","source":"https://en.wikipedia.org/wiki/Kansas City","note":""},"geometry":{"coordinates":[39.0997265,-94.5785667],"type":"Point"}}