{"type":"Feature","properties":{"name":"Khartoum","founded":"1821","abandoned":"","source":"https://en.wikipedia.org/wiki/Khartoum","note":""},"geometry":{"coordinates":[15.5006544,32.5598994],"type":"Point"}}