{"type":"Feature","properties":{"name":"Kiruna","founded":"","abandoned":"","source":"https://en.wikipedia.org/wiki/Kiruna","note":""},"geometry":{"coordinates":[67.8557995,20.225282],"type":"Point"}}