{"type":"Feature","properties":{"name":"Krasnodar","founded":"","abandoned":"","source":"https://en.wikipedia.org/wiki/Krasnodar","note":""},"geometry":{"coordinates":[45.03926740000001,38.9872209],"type":"Point"}}