{"type":"Feature","properties":{"name":"Kuwait City","founded":"","abandoned":"","source":"https://en.wikipedia.org/wiki/Kuwait City","note":""},"geometry":{"coordinates":[29.375859,47.9774052],"type":"Point"}}