{"type":"Feature","properties":{"name":"Leipzig","founded":"","abandoned":"","source":"https://en.wikipedia.org/wiki/Leipzig","note":""},"geometry":{"coordinates":[51.3396955,12.3730747],"type":"Point"}}