{"type":"Feature","properties":{"name":"Lhasa","founded":"","abandoned":"","source":"https://en.wikipedia.org/wiki/Lhasa","note":""},"geometry":{"coordinates":[29.65483799999999,91.140552],"type":"Point"}}