{"type":"Feature","properties":{"name":"Libreville","founded":"","abandoned":"","source":"https://en.wikipedia.org/wiki/Libreville","note":""},"geometry":{"coordinates":[0.4161976,9.4672676],"type":"Point"}}