{"type":"Feature","properties":{"name":"Lillehammer","founded":"","abandoned":"","source":"https://en.wikipedia.org/wiki/Lillehammer","note":""},"geometry":{"coordinates":[61.1152713,10.4662306],"type":"Point"}}