{"type":"Feature","properties":{"name":"Lilongwe","founded":"","abandoned":"","source":"https://en.wikipedia.org/wiki/Lilongwe","note":""},"geometry":{"coordinates":[-13.9626121,33.7741195],"type":"Point"}}