{"type":"Feature","properties":{"name":"Lincoln","founded":"","abandoned":"","source":"https://en.wikipedia.org/wiki/Lincoln","note":""},"geometry":{"coordinates":[40.8257625,-96.6851982],"type":"Point"}}