{"type":"Feature","properties":{"name":"Lleida","founded":"","abandoned":"","source":"https://en.wikipedia.org/wiki/Lleida","note":""},"geometry":{"coordinates":[41.6175899,0.6200146],"type":"Point"}}