{"type":"Feature","properties":{"name":"Louisville","founded":"","abandoned":"","source":"https://en.wikipedia.org/wiki/Louisville","note":""},"geometry":{"coordinates":[38.2526647,-85.7584557],"type":"Point"}}