{"type":"Feature","properties":{"name":"Maastricht","founded":"","abandoned":"","source":"https://en.wikipedia.org/wiki/Maastricht","note":""},"geometry":{"coordinates":[50.8513682,5.6909725],"type":"Point"}}