{"type":"Feature","properties":{"name":"Manzini","founded":"","abandoned":"","source":"https://en.wikipedia.org/wiki/Manzini","note":""},"geometry":{"coordinates":[-26.5081999,31.3713164],"type":"Point"}}