{"type":"Feature","properties":{"name":"Medellín","founded":"","abandoned":"","source":"https://en.wikipedia.org/wiki/Medellín","note":""},"geometry":{"coordinates":[6.244203,-75.5812119],"type":"Point"}}