{"type":"Feature","properties":{"name":"Minsk","founded":"","abandoned":"","source":"https://en.wikipedia.org/wiki/Minsk","note":""},"geometry":{"coordinates":[53.90453979999999,27.5615244],"type":"Point"}}