{"type":"Feature","properties":{"name":"Moscow","founded":"","abandoned":"","source":"https://en.wikipedia.org/wiki/Moscow","note":""},"geometry":{"coordinates":[55.755826,37.6172999],"type":"Point"}}