{"type":"Feature","properties":{"name":"Multan","founded":"","abandoned":"","source":"https://en.wikipedia.org/wiki/Multan","note":""},"geometry":{"coordinates":[30.157458,71.5249154],"type":"Point"}}