{"type":"Feature","properties":{"name":"Mumbai (Bombay)","founded":"","abandoned":"","source":"https://en.wikipedia.org/wiki/Mumbai (Bombay)","note":""},"geometry":{"coordinates":[19.0759837,72.8776559],"type":"Point"}}