{"type":"Feature","properties":{"name":"Mutare","founded":"","abandoned":"","source":"https://en.wikipedia.org/wiki/Mutare","note":""},"geometry":{"coordinates":[-18.9757714,32.650351],"type":"Point"}}