{"type":"Feature","properties":{"name":"Nashville","founded":"","abandoned":"","source":"https://en.wikipedia.org/wiki/Nashville","note":""},"geometry":{"coordinates":[36.1626638,-86.7816016],"type":"Point"}}