{"type":"Feature","properties":{"name":"Naypyidaw","founded":"","abandoned":"","source":"https://en.wikipedia.org/wiki/Naypyidaw","note":""},"geometry":{"coordinates":[19.7633057,96.07851040000001],"type":"Point"}}