{"type":"Feature","properties":{"name":"Niamey","founded":"","abandoned":"","source":"https://en.wikipedia.org/wiki/Niamey","note":""},"geometry":{"coordinates":[13.5115963,2.1253854],"type":"Point"}}