{"type":"Feature","properties":{"name":"Nice","founded":"","abandoned":"","source":"https://en.wikipedia.org/wiki/Nice","note":""},"geometry":{"coordinates":[43.7101728,7.261953200000001],"type":"Point"}}