{"type":"Feature","properties":{"name":"Norilsk","founded":"","abandoned":"","source":"https://en.wikipedia.org/wiki/Norilsk","note":""},"geometry":{"coordinates":[69.35579,88.1892939],"type":"Point"}}