{"type":"Feature","properties":{"name":"Norrköping","founded":"","abandoned":"","source":"https://en.wikipedia.org/wiki/Norrköping","note":""},"geometry":{"coordinates":[58.587745,16.192421],"type":"Point"}}