{"type":"Feature","properties":{"name":"Ny-Ålesund","founded":"","abandoned":"","source":"https://en.wikipedia.org/wiki/Ny-Ålesund","note":""},"geometry":{"coordinates":[78.9235381,11.9098952],"type":"Point"}}