{"type":"Feature","properties":{"name":"Omdurman","founded":"","abandoned":"","source":"https://en.wikipedia.org/wiki/Omdurman","note":""},"geometry":{"coordinates":[15.6475782,32.4806894],"type":"Point"}}