{"type":"Feature","properties":{"name":"Ottawa","founded":"","abandoned":"","source":"https://en.wikipedia.org/wiki/Ottawa","note":""},"geometry":{"coordinates":[45.4215296,-75.69719309999999],"type":"Point"}}