{"type":"Feature","properties":{"name":"Palermo","founded":"","abandoned":"","source":"https://en.wikipedia.org/wiki/Palermo","note":""},"geometry":{"coordinates":[38.1156879,13.3612671],"type":"Point"}}