{"type":"Feature","properties":{"name":"Peshawar","founded":"","abandoned":"","source":"https://en.wikipedia.org/wiki/Peshawar","note":""},"geometry":{"coordinates":[34.0151366,71.5249154],"type":"Point"}}