{"type":"Feature","properties":{"name":"Porto Alegre","founded":"","abandoned":"","source":"https://en.wikipedia.org/wiki/Porto Alegre","note":""},"geometry":{"coordinates":[-30.0346471,-51.2176584],"type":"Point"}}