{"type":"Feature","properties":{"name":"Port Harcourt","founded":"","abandoned":"","source":"https://en.wikipedia.org/wiki/Port Harcourt","note":""},"geometry":{"coordinates":[4.815554,7.0498442],"type":"Point"}}