{"type":"Feature","properties":{"name":"Providence","founded":"","abandoned":"","source":"https://en.wikipedia.org/wiki/Providence","note":""},"geometry":{"coordinates":[41.8239891,-71.4128343],"type":"Point"}}