{"type":"Feature","properties":{"name":"Recife","founded":"","abandoned":"","source":"https://en.wikipedia.org/wiki/Recife","note":""},"geometry":{"coordinates":[-8.0475622,-34.8769643],"type":"Point"}}