{"type":"Feature","properties":{"name":"Rio de Janeiro","founded":"","abandoned":"","source":"https://en.wikipedia.org/wiki/Rio de Janeiro","note":""},"geometry":{"coordinates":[-22.9068467,-43.1728965],"type":"Point"}}