{"type":"Feature","properties":{"name":"Roseau","founded":"","abandoned":"","source":"https://en.wikipedia.org/wiki/Roseau","note":""},"geometry":{"coordinates":[15.3091676,-61.37935539999999],"type":"Point"}}