{"type":"Feature","properties":{"name":"Rouen","founded":"","abandoned":"","source":"https://en.wikipedia.org/wiki/Rouen","note":""},"geometry":{"coordinates":[49.44323199999999,1.099971],"type":"Point"}}