{"type":"Feature","properties":{"name":"Rovaniemi","founded":"","abandoned":"","source":"https://en.wikipedia.org/wiki/Rovaniemi","note":""},"geometry":{"coordinates":[66.50394779999999,25.7293906],"type":"Point"}}