{"type":"Feature","properties":{"name":"San Salvador","founded":"","abandoned":"","source":"https://en.wikipedia.org/wiki/San Salvador","note":""},"geometry":{"coordinates":[13.6929403,-89.2181911],"type":"Point"}}