{"type":"Feature","properties":{"name":"San Carlos de Bariloche","founded":"","abandoned":"","source":"https://en.wikipedia.org/wiki/San Carlos de Bariloche","note":""},"geometry":{"coordinates":[-41.1334722,-71.3102778],"type":"Point"}}