{"type":"Feature","properties":{"name":"Santo Domingo","founded":"","abandoned":"","source":"https://en.wikipedia.org/wiki/Santo Domingo","note":""},"geometry":{"coordinates":[18.4860575,-69.93121169999999],"type":"Point"}}