{"type":"Feature","properties":{"name":"Sinop","founded":"","abandoned":"","source":"https://en.wikipedia.org/wiki/Sinop","note":""},"geometry":{"coordinates":[-11.8608456,-55.5095451],"type":"Point"}}