{"type":"Feature","properties":{"name":"Sippar","founded":"-4000","abandoned":"-1000","source":"https://en.wikipedia.org/wiki/Sippar","note":""},"geometry":{"coordinates":[33.058829,44.252153],"type":"Point"}}