{"type":"Feature","properties":{"name":"Sri Jayawardenapura-Kotte","founded":"","abandoned":"","source":"https://en.wikipedia.org/wiki/Sri Jayawardenapura-Kotte","note":""},"geometry":{"coordinates":[6.894002899999999,79.90515649999999],"type":"Point"}}