{"type":"Feature","properties":{"name":"St. John's","founded":"","abandoned":"","source":"https://en.wikipedia.org/wiki/St. John's","note":""},"geometry":{"coordinates":[47.5615096,-52.7125768],"type":"Point"}}