{"type":"Feature","properties":{"name":"Sukhumi","founded":"","abandoned":"","source":"https://en.wikipedia.org/wiki/Sukhumi","note":""},"geometry":{"coordinates":[43.0015252,41.0234153],"type":"Point"}}