{"type":"Feature","properties":{"name":"São Tomé","founded":"","abandoned":"","source":"https://en.wikipedia.org/wiki/São Tomé","note":""},"geometry":{"coordinates":[0.3301924,6.733343],"type":"Point"}}