{"type":"Feature","properties":{"name":"São José dos Campos","founded":"","abandoned":"","source":"https://en.wikipedia.org/wiki/São José dos Campos","note":""},"geometry":{"coordinates":[-23.223701,-45.9009074],"type":"Point"}}