{"type":"Feature","properties":{"name":"Tabriz","founded":"","abandoned":"","source":"https://en.wikipedia.org/wiki/Tabriz","note":""},"geometry":{"coordinates":[38.096239,46.2738013],"type":"Point"}}