{"type":"Feature","properties":{"name":"Tallinn","founded":"","abandoned":"","source":"https://en.wikipedia.org/wiki/Tallinn","note":""},"geometry":{"coordinates":[59.43696079999999,24.7535747],"type":"Point"}}