{"type":"Feature","properties":{"name":"Tampico","founded":"","abandoned":"","source":"https://en.wikipedia.org/wiki/Tampico","note":""},"geometry":{"coordinates":[22.2331041,-97.861099],"type":"Point"}}