{"type":"Feature","properties":{"name":"Temuco","founded":"","abandoned":"","source":"https://en.wikipedia.org/wiki/Temuco","note":""},"geometry":{"coordinates":[-38.7359018,-72.5903739],"type":"Point"}}