{"type":"Feature","properties":{"name":"Tezpur","founded":"","abandoned":"","source":"https://en.wikipedia.org/wiki/Tezpur","note":""},"geometry":{"coordinates":[26.6528495,92.7925592],"type":"Point"}}