{"type":"Feature","properties":{"name":"Thimphu","founded":"","abandoned":"","source":"https://en.wikipedia.org/wiki/Thimphu","note":""},"geometry":{"coordinates":[27.4727924,89.6392863],"type":"Point"}}