{"type":"Feature","properties":{"name":"Thunder Bay","founded":"","abandoned":"","source":"https://en.wikipedia.org/wiki/Thunder Bay","note":""},"geometry":{"coordinates":[48.3808951,-89.2476823],"type":"Point"}}