{"type":"Feature","properties":{"name":"Upernavik","founded":"","abandoned":"","source":"https://en.wikipedia.org/wiki/Upernavik","note":""},"geometry":{"coordinates":[72.7862882,-56.1375527],"type":"Point"}}