{"type":"Feature","properties":{"name":"Valdivia","founded":"","abandoned":"","source":"https://en.wikipedia.org/wiki/Valdivia","note":""},"geometry":{"coordinates":[-39.8195857,-73.2452103],"type":"Point"}}