{"type":"Feature","properties":{"name":"Vilnius","founded":"","abandoned":"","source":"https://en.wikipedia.org/wiki/Vilnius","note":""},"geometry":{"coordinates":[54.6871555,25.2796514],"type":"Point"}}