{"type":"Feature","properties":{"name":"Visakhapatnam","founded":"","abandoned":"","source":"https://en.wikipedia.org/wiki/Visakhapatnam","note":""},"geometry":{"coordinates":[17.6868159,83.2184815],"type":"Point"}}