{"type":"Feature","properties":{"name":"Willemstad","founded":"","abandoned":"","source":"https://en.wikipedia.org/wiki/Willemstad","note":""},"geometry":{"coordinates":[12.1224221,-68.8824233],"type":"Point"}}