{"type":"Feature","properties":{"name":"Yangon","founded":"","abandoned":"","source":"https://en.wikipedia.org/wiki/Yangon","note":""},"geometry":{"coordinates":[16.8660694,96.19513200000002],"type":"Point"}}