{"type":"Feature","properties":{"name":"Yaroslavl","founded":"","abandoned":"","source":"https://en.wikipedia.org/wiki/Yaroslavl","note":""},"geometry":{"coordinates":[57.62607440000001,39.8844709],"type":"Point"}}