{"type":"Feature","properties":{"name":"Yerevan","founded":"","abandoned":"","source":"https://en.wikipedia.org/wiki/Yerevan","note":""},"geometry":{"coordinates":[40.1791857,44.4991029],"type":"Point"}}