{"type":"Feature","properties":{"name":"Zagreb","founded":"","abandoned":"","source":"https://en.wikipedia.org/wiki/Zagreb","note":""},"geometry":{"coordinates":[45.8150108,15.9819189],"type":"Point"}}