{"type":"Feature","properties":{"name":"Östersund","founded":"","abandoned":"","source":"https://en.wikipedia.org/wiki/Östersund","note":""},"geometry":{"coordinates":[63.1766832,14.6360681],"type":"Point"}}